README.md
setup.py
model_mart/__init__.py
model_mart/model_mart_utils.py
model_mart.egg-info/PKG-INFO
model_mart.egg-info/SOURCES.txt
model_mart.egg-info/dependency_links.txt
model_mart.egg-info/requires.txt
model_mart.egg-info/top_level.txt