Metadata-Version: 2.1
Name: model-mart
Version: 0.0.5
Summary: sdk help users to use model market
Home-page: https://gitlab.stonewise.cn/mlsys/model-mart.git
Author: SoutherLea
Author-email: lizhengnan@stonewise.cn
Classifier: Programming Language :: Python :: 3
Classifier: License :: OSI Approved :: MIT License
Classifier: Operating System :: OS Independent
Requires-Python: >=3.5
